<?xml version="1.0" encoding="UTF-8" standalone="yes"?>
<p:sldLayout xmlns:a="http://schemas.openxmlformats.org/drawingml/2006/main" xmlns:r="http://schemas.openxmlformats.org/officeDocument/2006/relationships" xmlns:p="http://schemas.openxmlformats.org/presentationml/2006/main" preserve="1" userDrawn="1"><p:cSld name="4_Team small (WH)"><p:bg><p:bgPr><a:solidFill><a:schemeClr val="tx1"/></a:solidFill><a:effectLst/></p:bgPr></p:bg><p:spTree><p:nvGrpSpPr><p:cNvPr id="1" name=""/><p:cNvGrpSpPr/><p:nvPr/></p:nvGrpSpPr><p:grpSpPr><a:xfrm><a:off x="0" y="0"/><a:ext cx="0" cy="0"/><a:chOff x="0" y="0"/><a:chExt cx="0" cy="0"/></a:xfrm></p:grpSpPr><p:sp><p:nvSpPr><p:cNvPr id="9" name="Graphic 7"><a:extLst><a:ext uri="{FF2B5EF4-FFF2-40B4-BE49-F238E27FC236}"><a16:creationId xmlns:a16="http://schemas.microsoft.com/office/drawing/2014/main" id="{1BEEDCC2-B0D2-2EF9-3087-67714B45660F}"/></a:ext></a:extLst></p:cNvPr><p:cNvSpPr/><p:nvPr userDrawn="1"/></p:nvSpPr><p:spPr><a:xfrm><a:off x="431802" y="2105286"/><a:ext cx="3633085" cy="3633194"/></a:xfrm><a:custGeom><a:avLst/><a:gdLst><a:gd name="csX0" fmla="*/ 3907074 w 4321284"/><a:gd name="csY0" fmla="*/ 0 h 4321414"/><a:gd name="csX1" fmla="*/ 2572308 w 4321284"/><a:gd name="csY1" fmla="*/ 0 h 4321414"/><a:gd name="csX2" fmla="*/ 2157967 w 4321284"/><a:gd name="csY2" fmla="*/ 414341 h 4321414"/><a:gd name="csX3" fmla="*/ 2157967 w 4321284"/><a:gd name="csY3" fmla="*/ 1648490 h 4321414"/><a:gd name="csX4" fmla="*/ 1648621 w 4321284"/><a:gd name="csY4" fmla="*/ 2157836 h 4321414"/><a:gd name="csX5" fmla="*/ 414341 w 4321284"/><a:gd name="csY5" fmla="*/ 2157836 h 4321414"/><a:gd name="csX6" fmla="*/ 40847 w 4321284"/><a:gd name="csY6" fmla="*/ 2392608 h 4321414"/><a:gd name="csX7" fmla="*/ 0 w 4321284"/><a:gd name="csY7" fmla="*/ 2572308 h 4321414"/><a:gd name="csX8" fmla="*/ 0 w 4321284"/><a:gd name="csY8" fmla="*/ 3907073 h 4321414"/><a:gd name="csX9" fmla="*/ 414341 w 4321284"/><a:gd name="csY9" fmla="*/ 4321414 h 4321414"/><a:gd name="csX10" fmla="*/ 1749107 w 4321284"/><a:gd name="csY10" fmla="*/ 4321414 h 4321414"/><a:gd name="csX11" fmla="*/ 2163448 w 4321284"/><a:gd name="csY11" fmla="*/ 3907073 h 4321414"/><a:gd name="csX12" fmla="*/ 2163448 w 4321284"/><a:gd name="csY12" fmla="*/ 2672924 h 4321414"/><a:gd name="csX13" fmla="*/ 2672794 w 4321284"/><a:gd name="csY13" fmla="*/ 2163578 h 4321414"/><a:gd name="csX14" fmla="*/ 3906944 w 4321284"/><a:gd name="csY14" fmla="*/ 2163578 h 4321414"/><a:gd name="csX15" fmla="*/ 4280438 w 4321284"/><a:gd name="csY15" fmla="*/ 1928807 h 4321414"/><a:gd name="csX16" fmla="*/ 4321285 w 4321284"/><a:gd name="csY16" fmla="*/ 1749107 h 4321414"/><a:gd name="csX17" fmla="*/ 4321285 w 4321284"/><a:gd name="csY17" fmla="*/ 414341 h 4321414"/><a:gd name="csX18" fmla="*/ 3906944 w 4321284"/><a:gd name="csY18" fmla="*/ 0 h 4321414"/></a:gdLst><a:ahLst/><a:cxnLst><a:cxn ang="0"><a:pos x="csX0" y="csY0"/></a:cxn><a:cxn ang="0"><a:pos x="csX1" y="csY1"/></a:cxn><a:cxn ang="0"><a:pos x="csX2" y="csY2"/></a:cxn><a:cxn ang="0"><a:pos x="csX3" y="csY3"/></a:cxn><a:cxn ang="0"><a:pos x="csX4" y="csY4"/></a:cxn><a:cxn ang="0"><a:pos x="csX5" y="csY5"/></a:cxn><a:cxn ang="0"><a:pos x="csX6" y="csY6"/></a:cxn><a:cxn ang="0"><a:pos x="csX7" y="csY7"/></a:cxn><a:cxn ang="0"><a:pos x="csX8" y="csY8"/></a:cxn><a:cxn ang="0"><a:pos x="csX9" y="csY9"/></a:cxn><a:cxn ang="0"><a:pos x="csX10" y="csY10"/></a:cxn><a:cxn ang="0"><a:pos x="csX11" y="csY11"/></a:cxn><a:cxn ang="0"><a:pos x="csX12" y="csY12"/></a:cxn><a:cxn ang="0"><a:pos x="csX13" y="csY13"/></a:cxn><a:cxn ang="0"><a:pos x="csX14" y="csY14"/></a:cxn><a:cxn ang="0"><a:pos x="csX15" y="csY15"/></a:cxn><a:cxn ang="0"><a:pos x="csX16" y="csY16"/></a:cxn><a:cxn ang="0"><a:pos x="csX17" y="csY17"/></a:cxn><a:cxn ang="0"><a:pos x="csX18" y="csY18"/></a:cxn></a:cxnLst><a:rect l="l" t="t" r="r" b="b"/><a:pathLst><a:path w="4321284" h="4321414"><a:moveTo><a:pt x="3907074" y="0"/></a:moveTo><a:lnTo><a:pt x="2572308" y="0"/></a:lnTo><a:cubicBezTo><a:pt x="2343409" y="0"/><a:pt x="2157967" y="185573"/><a:pt x="2157967" y="414341"/></a:cubicBezTo><a:lnTo><a:pt x="2157967" y="1648490"/></a:lnTo><a:cubicBezTo><a:pt x="2157967" y="1929720"/><a:pt x="1929982" y="2157836"/><a:pt x="1648621" y="2157836"/></a:cubicBezTo><a:lnTo><a:pt x="414341" y="2157836"/></a:lnTo><a:cubicBezTo><a:pt x="249910" y="2157836"/><a:pt x="107794" y="2253624"/><a:pt x="40847" y="2392608"/></a:cubicBezTo><a:cubicBezTo><a:pt x="14616" y="2446896"/><a:pt x="0" y="2507840"/><a:pt x="0" y="2572308"/></a:cubicBezTo><a:lnTo><a:pt x="0" y="3907073"/></a:lnTo><a:cubicBezTo><a:pt x="0" y="4135972"/><a:pt x="185573" y="4321414"/><a:pt x="414341" y="4321414"/></a:cubicBezTo><a:lnTo><a:pt x="1749107" y="4321414"/></a:lnTo><a:cubicBezTo><a:pt x="1978006" y="4321414"/><a:pt x="2163448" y="4135842"/><a:pt x="2163448" y="3907073"/></a:cubicBezTo><a:lnTo><a:pt x="2163448" y="2672924"/></a:lnTo><a:cubicBezTo><a:pt x="2163448" y="2391694"/><a:pt x="2391434" y="2163578"/><a:pt x="2672794" y="2163578"/></a:cubicBezTo><a:lnTo><a:pt x="3906944" y="2163578"/></a:lnTo><a:cubicBezTo><a:pt x="4071375" y="2163578"/><a:pt x="4213491" y="2067790"/><a:pt x="4280438" y="1928807"/></a:cubicBezTo><a:cubicBezTo><a:pt x="4306669" y="1874518"/><a:pt x="4321285" y="1813574"/><a:pt x="4321285" y="1749107"/></a:cubicBezTo><a:lnTo><a:pt x="4321285" y="414341"/></a:lnTo><a:cubicBezTo><a:pt x="4321285" y="185442"/><a:pt x="4135712" y="0"/><a:pt x="3906944" y="0"/></a:cubicBezTo><a:close/></a:path></a:pathLst></a:custGeom><a:solidFill><a:schemeClr val="accent1"/></a:solidFill><a:ln w="13036" cap="flat"><a:noFill/><a:prstDash val="solid"/><a:miter/></a:ln></p:spPr><p:txBody><a:bodyPr/><a:lstStyle/><a:p><a:endParaRPr lang="en-US"/></a:p></p:txBody></p:sp><p:sp><p:nvSpPr><p:cNvPr id="17" name="Text Placeholder 5"><a:extLst><a:ext uri="{FF2B5EF4-FFF2-40B4-BE49-F238E27FC236}"><a16:creationId xmlns:a16="http://schemas.microsoft.com/office/drawing/2014/main" id="{8F873EB5-4E1C-F266-BB92-CD98D1CF6D6E}"/></a:ext></a:extLst></p:cNvPr><p:cNvSpPr><a:spLocks noGrp="1"/></p:cNvSpPr><p:nvPr><p:ph type="body" sz="quarter" idx="15" hasCustomPrompt="1"/></p:nvPr></p:nvSpPr><p:spPr><a:xfrm><a:off x="4269807" y="2731216"/><a:ext cx="3654994" cy="320483"/></a:xfrm><a:prstGeom prst="rect"><a:avLst/></a:prstGeom></p:spPr><p:txBody><a:bodyPr lIns="0"><a:noAutofit/></a:bodyPr><a:lstStyle><a:lvl1pPr marL="0" indent="0"><a:buNone/><a:defRPr sz="1800"><a:solidFill><a:schemeClr val="bg1"/></a:solidFill><a:latin typeface="+mj-lt"/><a:ea typeface="Noto Sans JP" panose="020B0200000000000000" pitchFamily="34" charset="-128"/><a:cs typeface="Noto Sans Medium" panose="020B0502040504020204" pitchFamily="34" charset="0"/></a:defRPr></a:lvl1pPr><a:lvl2pPr><a:defRPr sz="1000"/></a:lvl2pPr><a:lvl3pPr><a:defRPr sz="901"/></a:lvl3pPr><a:lvl4pPr><a:defRPr sz="800"/></a:lvl4pPr><a:lvl5pPr><a:defRPr sz="800"/></a:lvl5pPr></a:lstStyle><a:p><a:pPr lvl="0"/><a:r><a:rPr lang="en-US"/><a:t>Name Surname</a:t></a:r></a:p></p:txBody></p:sp><p:sp><p:nvSpPr><p:cNvPr id="18" name="Text Placeholder 16"><a:extLst><a:ext uri="{FF2B5EF4-FFF2-40B4-BE49-F238E27FC236}"><a16:creationId xmlns:a16="http://schemas.microsoft.com/office/drawing/2014/main" id="{242592A2-0205-02C0-55EA-FBBB66C6EBF6}"/></a:ext></a:extLst></p:cNvPr><p:cNvSpPr><a:spLocks noGrp="1"/></p:cNvSpPr><p:nvPr><p:ph type="body" sz="quarter" idx="28" hasCustomPrompt="1"/></p:nvPr></p:nvSpPr><p:spPr><a:xfrm><a:off x="4269806" y="3093398"/><a:ext cx="3654994" cy="320484"/></a:xfrm><a:prstGeom prst="rect"><a:avLst/></a:prstGeom></p:spPr><p:txBody><a:bodyPr lIns="0"><a:noAutofit/></a:bodyPr><a:lstStyle><a:lvl1pPr marL="4763" indent="-4763"><a:buNone/><a:tabLst/><a:defRPr sz="1600" b="0" i="0"><a:solidFill><a:schemeClr val="accent1"/></a:solidFill><a:latin typeface="+mn-lt"/><a:ea typeface="Noto Sans JP Light" panose="020B0200000000000000" pitchFamily="34" charset="-128"/></a:defRPr></a:lvl1pPr><a:lvl2pPr><a:buNone/><a:defRPr/></a:lvl2pPr><a:lvl3pPr><a:buNone/><a:defRPr/></a:lvl3pPr><a:lvl4pPr><a:buNone/><a:defRPr/></a:lvl4pPr><a:lvl5pPr><a:buNone/><a:defRPr/></a:lvl5pPr></a:lstStyle><a:p><a:pPr lvl="0"/><a:r><a:rPr lang="en-US"/><a:t>Job title</a:t></a:r></a:p></p:txBody></p:sp><p:sp><p:nvSpPr><p:cNvPr id="26" name="Picture Placeholder 12"><a:extLst><a:ext uri="{FF2B5EF4-FFF2-40B4-BE49-F238E27FC236}"><a16:creationId xmlns:a16="http://schemas.microsoft.com/office/drawing/2014/main" id="{D770246B-7B9E-0D6A-3563-F37B121485F9}"/></a:ext></a:extLst></p:cNvPr><p:cNvSpPr><a:spLocks noGrp="1"/></p:cNvSpPr><p:nvPr><p:ph type="pic" sz="quarter" idx="39"/></p:nvPr></p:nvSpPr><p:spPr><a:xfrm><a:off x="517273" y="2180036"/><a:ext cx="3467586" cy="3468316"/></a:xfrm><a:prstGeom prst="roundRect"><a:avLst><a:gd name="adj" fmla="val 8872"/></a:avLst></a:prstGeom><a:solidFill><a:schemeClr val="tx1"/></a:solidFill></p:spPr><p:txBody><a:bodyPr/><a:lstStyle/><a:p><a:r><a:rPr lang="de-DE"/><a:t>Bild durch Klicken auf Symbol hinzufügen</a:t></a:r><a:endParaRPr lang="en-US"/></a:p></p:txBody></p:sp><p:sp><p:nvSpPr><p:cNvPr id="31" name="Text Placeholder 4"><a:extLst><a:ext uri="{FF2B5EF4-FFF2-40B4-BE49-F238E27FC236}"><a16:creationId xmlns:a16="http://schemas.microsoft.com/office/drawing/2014/main" id="{14AEEDB8-0FFC-FC4E-7095-3265608FBB3A}"/></a:ext></a:extLst></p:cNvPr><p:cNvSpPr><a:spLocks noGrp="1"/></p:cNvSpPr><p:nvPr><p:ph type="body" sz="quarter" idx="12" hasCustomPrompt="1"/></p:nvPr></p:nvSpPr><p:spPr><a:xfrm><a:off x="434976" y="335419"/><a:ext cx="6551612" cy="215444"/></a:xfrm><a:prstGeom prst="rect"><a:avLst/></a:prstGeom></p:spPr><p:txBody><a:bodyPr wrap="square" lIns="72000" tIns="0" rIns="0" bIns="0" anchor="b"><a:noAutofit/></a:bodyPr><a:lstStyle><a:lvl1pPr><a:buNone/><a:defRPr sz="1400" b="0" i="0" spc="101" baseline="0"><a:solidFill><a:schemeClr val="accent1"/></a:solidFill><a:latin typeface="IBM Plex Mono" panose="020B0509050203000203" pitchFamily="49" charset="77"/><a:ea typeface="Noto Sans JP" panose="020B0200000000000000" pitchFamily="34" charset="-128"/></a:defRPr></a:lvl1pPr><a:lvl2pPr><a:defRPr sz="1600"/></a:lvl2pPr><a:lvl3pPr><a:defRPr sz="1400"/></a:lvl3pPr><a:lvl4pPr><a:defRPr sz="1200"/></a:lvl4pPr><a:lvl5pPr><a:defRPr sz="1200"/></a:lvl5pPr></a:lstStyle><a:p><a:pPr lvl="0"/><a:r><a:rPr lang="en-US"/><a:t>Eyebrow</a:t></a:r></a:p></p:txBody></p:sp><p:sp><p:nvSpPr><p:cNvPr id="32" name="Fußzeilenplatzhalter 31"><a:extLst><a:ext uri="{FF2B5EF4-FFF2-40B4-BE49-F238E27FC236}"><a16:creationId xmlns:a16="http://schemas.microsoft.com/office/drawing/2014/main" id="{56BCC2D8-CBAD-9CE7-E467-B51B668FC401}"/></a:ext></a:extLst></p:cNvPr><p:cNvSpPr><a:spLocks noGrp="1"/></p:cNvSpPr><p:nvPr><p:ph type="ftr" sz="quarter" idx="43"/></p:nvPr></p:nvSpPr><p:spPr/><p:txBody><a:bodyPr/><a:lstStyle><a:lvl1pPr><a:defRPr><a:solidFill><a:schemeClr val="bg1"/></a:solidFill></a:defRPr></a:lvl1pPr></a:lstStyle><a:p><a:endParaRPr lang="de-DE"><a:solidFill><a:schemeClr val="bg1"/></a:solidFill></a:endParaRPr></a:p></p:txBody></p:sp><p:sp><p:nvSpPr><p:cNvPr id="33" name="Foliennummernplatzhalter 32"><a:extLst><a:ext uri="{FF2B5EF4-FFF2-40B4-BE49-F238E27FC236}"><a16:creationId xmlns:a16="http://schemas.microsoft.com/office/drawing/2014/main" id="{D83C555D-F53E-7878-D414-5AD13510E4EA}"/></a:ext></a:extLst></p:cNvPr><p:cNvSpPr><a:spLocks noGrp="1"/></p:cNvSpPr><p:nvPr><p:ph type="sldNum" sz="quarter" idx="44"/></p:nvPr></p:nvSpPr><p:spPr/><p:txBody><a:bodyPr/><a:lstStyle><a:lvl1pPr><a:defRPr><a:solidFill><a:schemeClr val="bg1"/></a:solidFill></a:defRPr></a:lvl1pPr></a:lstStyle><a:p><a:fld id="{99EF9B8F-7997-3D46-8624-83D2A6388658}" type="slidenum"><a:rPr lang="en-GB" smtClean="0"/><a:pPr/><a:t>‹Nr.›</a:t></a:fld><a:endParaRPr lang="en-GB"/></a:p></p:txBody></p:sp><p:sp><p:nvSpPr><p:cNvPr id="2" name="Text Placeholder 16"><a:extLst><a:ext uri="{FF2B5EF4-FFF2-40B4-BE49-F238E27FC236}"><a16:creationId xmlns:a16="http://schemas.microsoft.com/office/drawing/2014/main" id="{21CDD5EF-7211-7C14-D50B-EAA729D59B2B}"/></a:ext></a:extLst></p:cNvPr><p:cNvSpPr><a:spLocks noGrp="1"/></p:cNvSpPr><p:nvPr><p:ph type="body" sz="quarter" idx="45" hasCustomPrompt="1"/></p:nvPr></p:nvSpPr><p:spPr><a:xfrm><a:off x="4269806" y="3593710"/><a:ext cx="3654994" cy="320484"/></a:xfrm><a:prstGeom prst="rect"><a:avLst/></a:prstGeom></p:spPr><p:txBody><a:bodyPr lIns="0"><a:noAutofit/></a:bodyPr><a:lstStyle><a:lvl1pPr marL="4763" indent="-4763"><a:buNone/><a:tabLst/><a:defRPr sz="1600" b="0" i="0"><a:solidFill><a:schemeClr val="bg1"/></a:solidFill><a:latin typeface="+mn-lt"/><a:ea typeface="Noto Sans JP Light" panose="020B0200000000000000" pitchFamily="34" charset="-128"/></a:defRPr></a:lvl1pPr><a:lvl2pPr><a:buNone/><a:defRPr/></a:lvl2pPr><a:lvl3pPr><a:buNone/><a:defRPr/></a:lvl3pPr><a:lvl4pPr><a:buNone/><a:defRPr/></a:lvl4pPr><a:lvl5pPr><a:buNone/><a:defRPr/></a:lvl5pPr></a:lstStyle><a:p><a:pPr lvl="0"/><a:r><a:rPr lang="en-US" err="1"/><a:t>name.surname@msqdx.com</a:t></a:r><a:endParaRPr lang="en-US"/></a:p></p:txBody></p:sp><p:sp><p:nvSpPr><p:cNvPr id="4" name="Text Placeholder 16"><a:extLst><a:ext uri="{FF2B5EF4-FFF2-40B4-BE49-F238E27FC236}"><a16:creationId xmlns:a16="http://schemas.microsoft.com/office/drawing/2014/main" id="{DBAFF138-671B-5332-656A-3F2A52D1B932}"/></a:ext></a:extLst></p:cNvPr><p:cNvSpPr><a:spLocks noGrp="1"/></p:cNvSpPr><p:nvPr><p:ph type="body" sz="quarter" idx="47" hasCustomPrompt="1"/></p:nvPr></p:nvSpPr><p:spPr><a:xfrm><a:off x="4269806" y="3925542"/><a:ext cx="3654994" cy="320484"/></a:xfrm><a:prstGeom prst="rect"><a:avLst/></a:prstGeom></p:spPr><p:txBody><a:bodyPr lIns="0"><a:noAutofit/></a:bodyPr><a:lstStyle><a:lvl1pPr marL="4763" indent="-4763"><a:buNone/><a:tabLst/><a:defRPr sz="1600" b="0" i="0"><a:solidFill><a:schemeClr val="bg1"/></a:solidFill><a:latin typeface="+mn-lt"/><a:ea typeface="Noto Sans JP Light" panose="020B0200000000000000" pitchFamily="34" charset="-128"/></a:defRPr></a:lvl1pPr><a:lvl2pPr><a:buNone/><a:defRPr/></a:lvl2pPr><a:lvl3pPr><a:buNone/><a:defRPr/></a:lvl3pPr><a:lvl4pPr><a:buNone/><a:defRPr/></a:lvl4pPr><a:lvl5pPr><a:buNone/><a:defRPr/></a:lvl5pPr></a:lstStyle><a:p><a:pPr lvl="0"/><a:r><a:rPr lang="en-US"/><a:t>+44 123 45 67 89</a:t></a:r></a:p></p:txBody></p:sp><p:sp><p:nvSpPr><p:cNvPr id="7" name="Text Placeholder 7"><a:extLst><a:ext uri="{FF2B5EF4-FFF2-40B4-BE49-F238E27FC236}"><a16:creationId xmlns:a16="http://schemas.microsoft.com/office/drawing/2014/main" id="{827FA9C0-D4CD-0B8A-55AE-A2FAE21F4440}"/></a:ext></a:extLst></p:cNvPr><p:cNvSpPr><a:spLocks noGrp="1"/></p:cNvSpPr><p:nvPr><p:ph type="body" sz="quarter" idx="18" hasCustomPrompt="1"/></p:nvPr></p:nvSpPr><p:spPr><a:xfrm><a:off x="4271706" y="4423692"/><a:ext cx="2714882" cy="1224660"/></a:xfrm><a:prstGeom prst="rect"><a:avLst/></a:prstGeom></p:spPr><p:txBody><a:bodyPr lIns="0" rIns="72000" anchor="b"/><a:lstStyle><a:lvl1pPr marL="0" indent="0" algn="l"><a:spcBef><a:spcPts val="600"/></a:spcBef><a:buNone/><a:defRPr sz="1600" b="0" i="0"><a:solidFill><a:schemeClr val="bg1"/></a:solidFill><a:latin typeface="+mn-lt"/><a:ea typeface="Noto Sans JP Light" panose="020B0200000000000000" pitchFamily="34" charset="-128"/></a:defRPr></a:lvl1pPr><a:lvl2pPr><a:defRPr><a:solidFill><a:schemeClr val="tx1"/></a:solidFill></a:defRPr></a:lvl2pPr><a:lvl3pPr><a:defRPr><a:solidFill><a:schemeClr val="tx1"/></a:solidFill></a:defRPr></a:lvl3pPr><a:lvl4pPr><a:defRPr><a:solidFill><a:schemeClr val="tx1"/></a:solidFill></a:defRPr></a:lvl4pPr><a:lvl5pPr><a:defRPr><a:solidFill><a:schemeClr val="tx1"/></a:solidFill></a:defRPr></a:lvl5pPr></a:lstStyle><a:p><a:pPr lvl="0"/><a:r><a:rPr lang="en-US"/><a:t>MSQ DX </a:t></a:r></a:p><a:p><a:pPr lvl="0"/><a:r><a:rPr lang="en-US"/><a:t>71 Fifth Avenue 8th Floor </a:t></a:r></a:p><a:p><a:pPr lvl="0"/><a:r><a:rPr lang="en-US"/><a:t>New York NY 10003</a:t></a:r></a:p></p:txBody></p:sp><p:sp><p:nvSpPr><p:cNvPr id="5" name="Textfeld 4"><a:extLst><a:ext uri="{FF2B5EF4-FFF2-40B4-BE49-F238E27FC236}"><a16:creationId xmlns:a16="http://schemas.microsoft.com/office/drawing/2014/main" id="{606A097C-71C7-3DEF-8489-8E3667508B38}"/></a:ext></a:extLst></p:cNvPr><p:cNvSpPr txBox="1"/><p:nvPr userDrawn="1"/></p:nvSpPr><p:spPr><a:xfrm><a:off x="7931960" y="4826333"/><a:ext cx="3935407" cy="861774"/></a:xfrm><a:prstGeom prst="rect"><a:avLst/></a:prstGeom><a:noFill/></p:spPr><p:txBody><a:bodyPr wrap="square" rtlCol="0"><a:spAutoFit/></a:bodyPr><a:lstStyle/><a:p><a:r><a:rPr lang="en-GB" sz="1000" b="0" i="0" noProof="1"><a:solidFill><a:schemeClr val="bg1"/></a:solidFill><a:latin typeface="+mn-lt"/><a:ea typeface="Noto Sans JP Light" panose="020B0300000000000000" pitchFamily="34" charset="-128"/></a:rPr><a:t>All content is based on the current state of communication. </a:t></a:r><a:br><a:rPr lang="en-GB" sz="1000" b="0" i="0" noProof="1"><a:solidFill><a:schemeClr val="bg1"/></a:solidFill><a:latin typeface="+mn-lt"/><a:ea typeface="Noto Sans JP Light" panose="020B0300000000000000" pitchFamily="34" charset="-128"/></a:rPr></a:br><a:r><a:rPr lang="en-GB" sz="1000" b="0" i="0" noProof="1"><a:solidFill><a:schemeClr val="bg1"/></a:solidFill><a:latin typeface="+mn-lt"/><a:ea typeface="Noto Sans JP Light" panose="020B0300000000000000" pitchFamily="34" charset="-128"/></a:rPr><a:t>Subject to change. This document of MSQ DX is only intended </a:t></a:r><a:br><a:rPr lang="en-GB" sz="1000" b="0" i="0" noProof="1"><a:solidFill><a:schemeClr val="bg1"/></a:solidFill><a:latin typeface="+mn-lt"/><a:ea typeface="Noto Sans JP Light" panose="020B0300000000000000" pitchFamily="34" charset="-128"/></a:rPr></a:br><a:r><a:rPr lang="en-GB" sz="1000" b="0" i="0" noProof="1"><a:solidFill><a:schemeClr val="bg1"/></a:solidFill><a:latin typeface="+mn-lt"/><a:ea typeface="Noto Sans JP Light" panose="020B0300000000000000" pitchFamily="34" charset="-128"/></a:rPr><a:t>for the client. It belongs to the agency until its explicit transfer </a:t></a:r><a:br><a:rPr lang="en-GB" sz="1000" b="0" i="0" noProof="1"><a:solidFill><a:schemeClr val="bg1"/></a:solidFill><a:latin typeface="+mn-lt"/><a:ea typeface="Noto Sans JP Light" panose="020B0300000000000000" pitchFamily="34" charset="-128"/></a:rPr></a:br><a:r><a:rPr lang="en-GB" sz="1000" b="0" i="0" noProof="1"><a:solidFill><a:schemeClr val="bg1"/></a:solidFill><a:latin typeface="+mn-lt"/><a:ea typeface="Noto Sans JP Light" panose="020B0300000000000000" pitchFamily="34" charset="-128"/></a:rPr><a:t>of usage rights. Any adaptation, utilization, copy and/or </a:t></a:r><a:br><a:rPr lang="en-GB" sz="1000" b="0" i="0" noProof="1"><a:solidFill><a:schemeClr val="bg1"/></a:solidFill><a:latin typeface="+mn-lt"/><a:ea typeface="Noto Sans JP Light" panose="020B0300000000000000" pitchFamily="34" charset="-128"/></a:rPr></a:br><a:r><a:rPr lang="en-GB" sz="1000" b="0" i="0" noProof="1"><a:solidFill><a:schemeClr val="bg1"/></a:solidFill><a:latin typeface="+mn-lt"/><a:ea typeface="Noto Sans JP Light" panose="020B0300000000000000" pitchFamily="34" charset="-128"/></a:rPr><a:t>professional spreading has to be approved by the agency.</a:t></a:r></a:p></p:txBody></p:sp><p:sp><p:nvSpPr><p:cNvPr id="6" name="Titel 5"><a:extLst><a:ext uri="{FF2B5EF4-FFF2-40B4-BE49-F238E27FC236}"><a16:creationId xmlns:a16="http://schemas.microsoft.com/office/drawing/2014/main" id="{3CDCEDC6-17BF-5E51-0752-230A9AA07EB4}"/></a:ext></a:extLst></p:cNvPr><p:cNvSpPr><a:spLocks noGrp="1"/></p:cNvSpPr><p:nvPr><p:ph type="title" hasCustomPrompt="1"/></p:nvPr></p:nvSpPr><p:spPr/><p:txBody><a:bodyPr/><a:lstStyle/><a:p><a:r><a:rPr lang="de-DE"/><a:t>Headline</a:t></a:r></a:p></p:txBody></p:sp></p:spTree><p:extLst><p:ext uri="{BB962C8B-B14F-4D97-AF65-F5344CB8AC3E}"><p14:creationId xmlns:p14="http://schemas.microsoft.com/office/powerpoint/2010/main" val="2955371226"/></p:ext></p:extLst></p:cSld><p:clrMapOvr><a:masterClrMapping/></p:clrMapOvr></p:sldLayout>